{"_ts":[1535785398],"_r":{"breakdown":{"html":{"bytes":[10949],"requests":[4]},"js":{"bytes":[443461],"requests":[28]},"css":{"bytes":[69205],"requests":[20]},"image":{"bytes":[165320],"requests":[9]},"flash":{"bytes":[0],"requests":[0]},"font":{"bytes":[114569],"requests":[4]},"video":{"bytes":[0],"requests":[0]},"other":{"bytes":[613],"requests":[2]}},"date":[1535785398],"domElements":[405],"domInteractive":[2902],"firstPaint":[2902.2000000004],"fullyLoaded":[5699],"id":["180901_WG_b20f6b76bb22e2db64be282a15f8a8fd"],"loadTime":[5654],"render":[2900],"SpeedIndex":[3199],"TTFB":[1505],"videoFrames":[[{"_i":"ms_000000.jpg","_t":0,"_vc":0},{"_i":"ms_002900.jpg","_t":2900,"_vc":10},{"_i":"ms_003133.jpg","_t":3133,"_vc":38},{"_i":"ms_003167.jpg","_t":3167,"_vc":39},{"_i":"ms_003200.jpg","_t":3200,"_vc":41},{"_i":"ms_003233.jpg","_t":3233,"_vc":99},{"_i":"ms_003367.jpg","_t":3367,"_vc":99},{"_i":"ms_003500.jpg","_t":3500,"_vc":99},{"_i":"ms_003533.jpg","_t":3533,"_vc":99},{"_i":"ms_003567.jpg","_t":3567,"_vc":99},{"_i":"ms_003600.jpg","_t":3600,"_vc":98},{"_i":"ms_003633.jpg","_t":3633,"_vc":98},{"_i":"ms_003667.jpg","_t":3667,"_vc":97},{"_i":"ms_004233.jpg","_t":4233,"_vc":99},{"_i":"ms_004733.jpg","_t":4733,"_vc":99},{"_i":"ms_004933.jpg","_t":4933,"_vc":100}]],"visualComplete":[4933],"lighthouse":[57],"pagespeed":[77]}}