{"_ts":[1514806195,1514850368],"_r":{"breakdown":{"html":{"bytes":[76271,54106],"requests":[18,17]},"js":{"bytes":[983833,905592],"requests":[21,20]},"css":{"bytes":[93478,86930],"requests":[5,5]},"image":{"bytes":[242080,277886],"requests":[15,15]},"flash":{"bytes":[0,0],"requests":[0,0]},"font":{"bytes":[232560,245039],"requests":[3,3]},"video":{"bytes":[0,0],"requests":[0,0]},"other":{"bytes":[688647,724344],"requests":[18,18]}},"date":[1514806195,1514850368],"domElements":[737,737],"domInteractive":[1530,1579],"firstPaint":[1263,1256],"fullyLoaded":[11450,9372],"id":["180101_Q4_6faaaf66cb405ef1ec48082bd418eb3c","180101_VY_943ca27f22a629b6391984918c583c48"],"loadTime":[3244,3359],"render":[1267,1267],"SpeedIndex":[1366,1361],"TTFB":[302,299],"videoFrames":[[{"_i":"ms_000000.jpg","_t":0,"_vc":0},{"_i":"ms_001267.jpg","_t":1267,"_vc":96},{"_i":"ms_001300.jpg","_t":1300,"_vc":96},{"_i":"ms_001333.jpg","_t":1333,"_vc":96},{"_i":"ms_001367.jpg","_t":1367,"_vc":96},{"_i":"ms_001400.jpg","_t":1400,"_vc":96},{"_i":"ms_001433.jpg","_t":1433,"_vc":96},{"_i":"ms_001467.jpg","_t":1467,"_vc":96},{"_i":"ms_001500.jpg","_t":1500,"_vc":96},{"_i":"ms_001533.jpg","_t":1533,"_vc":97},{"_i":"ms_001600.jpg","_t":1600,"_vc":99},{"_i":"ms_001700.jpg","_t":1700,"_vc":99},{"_i":"ms_001800.jpg","_t":1800,"_vc":99},{"_i":"ms_001900.jpg","_t":1900,"_vc":99},{"_i":"ms_002000.jpg","_t":2000,"_vc":99},{"_i":"ms_002100.jpg","_t":2100,"_vc":99},{"_i":"ms_002267.jpg","_t":2267,"_vc":99},{"_i":"ms_002300.jpg","_t":2300,"_vc":99},{"_i":"ms_002767.jpg","_t":2767,"_vc":99},{"_i":"ms_002833.jpg","_t":2833,"_vc":99},{"_i":"ms_002900.jpg","_t":2900,"_vc":99},{"_i":"ms_003000.jpg","_t":3000,"_vc":99},{"_i":"ms_003233.jpg","_t":3233,"_vc":99},{"_i":"ms_003567.jpg","_t":3567,"_vc":99},{"_i":"ms_003600.jpg","_t":3600,"_vc":99},{"_i":"ms_003700.jpg","_t":3700,"_vc":99},{"_i":"ms_003967.jpg","_t":3967,"_vc":99},{"_i":"ms_004733.jpg","_t":4733,"_vc":99},{"_i":"ms_004800.jpg","_t":4800,"_vc":99},{"_i":"ms_004900.jpg","_t":4900,"_vc":99},{"_i":"ms_005967.jpg","_t":5967,"_vc":99},{"_i":"ms_006500.jpg","_t":6500,"_vc":99},{"_i":"ms_006600.jpg","_t":6600,"_vc":99},{"_i":"ms_007500.jpg","_t":7500,"_vc":99},{"_i":"ms_007933.jpg","_t":7933,"_vc":99},{"_i":"ms_008433.jpg","_t":8433,"_vc":99},{"_i":"ms_008700.jpg","_t":8700,"_vc":99},{"_i":"ms_009000.jpg","_t":9000,"_vc":99},{"_i":"ms_009267.jpg","_t":9267,"_vc":99},{"_i":"ms_009500.jpg","_t":9500,"_vc":99},{"_i":"ms_009767.jpg","_t":9767,"_vc":99},{"_i":"ms_010133.jpg","_t":10133,"_vc":99},{"_i":"ms_010200.jpg","_t":10200,"_vc":99},{"_i":"ms_010300.jpg","_t":10300,"_vc":100}],[{"_i":"ms_000000.jpg","_t":0,"_vc":0},{"_i":"ms_001267.jpg","_t":1267,"_vc":96},{"_i":"ms_001300.jpg","_t":1300,"_vc":96},{"_i":"ms_001333.jpg","_t":1333,"_vc":96},{"_i":"ms_001367.jpg","_t":1367,"_vc":96},{"_i":"ms_001400.jpg","_t":1400,"_vc":96},{"_i":"ms_001433.jpg","_t":1433,"_vc":96},{"_i":"ms_001467.jpg","_t":1467,"_vc":97},{"_i":"ms_001500.jpg","_t":1500,"_vc":97},{"_i":"ms_001533.jpg","_t":1533,"_vc":97},{"_i":"ms_001600.jpg","_t":1600,"_vc":99},{"_i":"ms_001700.jpg","_t":1700,"_vc":99},{"_i":"ms_001800.jpg","_t":1800,"_vc":99},{"_i":"ms_001900.jpg","_t":1900,"_vc":99},{"_i":"ms_002000.jpg","_t":2000,"_vc":99},{"_i":"ms_002100.jpg","_t":2100,"_vc":99},{"_i":"ms_002267.jpg","_t":2267,"_vc":99},{"_i":"ms_002300.jpg","_t":2300,"_vc":99},{"_i":"ms_002433.jpg","_t":2433,"_vc":99},{"_i":"ms_003233.jpg","_t":3233,"_vc":99},{"_i":"ms_003700.jpg","_t":3700,"_vc":99},{"_i":"ms_003800.jpg","_t":3800,"_vc":99},{"_i":"ms_007567.jpg","_t":7567,"_vc":99},{"_i":"ms_008067.jpg","_t":8067,"_vc":99},{"_i":"ms_008100.jpg","_t":8100,"_vc":99},{"_i":"ms_008233.jpg","_t":8233,"_vc":99},{"_i":"ms_008633.jpg","_t":8633,"_vc":99},{"_i":"ms_009100.jpg","_t":9100,"_vc":99},{"_i":"ms_009267.jpg","_t":9267,"_vc":99},{"_i":"ms_009700.jpg","_t":9700,"_vc":99},{"_i":"ms_009800.jpg","_t":9800,"_vc":99},{"_i":"ms_009867.jpg","_t":9867,"_vc":100}]],"visualComplete":[10300,9867],"lighthouse":[54,45],"pagespeed":[83,83]}}